nonebot/adapters/kritor/__init__.py
nonebot/adapters/kritor/adapter.py
nonebot/adapters/kritor/bot.py
nonebot/adapters/kritor/compat.py
nonebot/adapters/kritor/config.py
nonebot/adapters/kritor/event.py
nonebot/adapters/kritor/exception.py
nonebot/adapters/kritor/message.py
nonebot/adapters/kritor/model.py
nonebot/adapters/kritor/permission.py
nonebot/adapters/kritor/protos/__init__.py
nonebot/adapters/kritor/protos/kritor/__init__.py
nonebot/adapters/kritor/protos/kritor/authentication/__init__.py
nonebot/adapters/kritor/protos/kritor/common/__init__.py
nonebot/adapters/kritor/protos/kritor/core/__init__.py
nonebot/adapters/kritor/protos/kritor/customization/__init__.py
nonebot/adapters/kritor/protos/kritor/developer/__init__.py
nonebot/adapters/kritor/protos/kritor/event/__init__.py
nonebot/adapters/kritor/protos/kritor/file/__init__.py
nonebot/adapters/kritor/protos/kritor/friend/__init__.py
nonebot/adapters/kritor/protos/kritor/group/__init__.py
nonebot/adapters/kritor/protos/kritor/guild/__init__.py
nonebot/adapters/kritor/protos/kritor/message/__init__.py
nonebot/adapters/kritor/protos/kritor/process/__init__.py
nonebot/adapters/kritor/protos/kritor/reverse/__init__.py
nonebot/adapters/kritor/protos/kritor/web/__init__.py
nonebot/adapters/kritor/utils.py
nonebot_adapter_kritor-0.3.2.dist-info/METADATA
nonebot_adapter_kritor-0.3.2.dist-info/WHEEL
nonebot_adapter_kritor-0.3.2.dist-info/entry_points.txt
nonebot_adapter_kritor-0.3.2.dist-info/licenses/LICENSE
nonebot_adapter_kritor-0.3.2.dist-info/RECORD
