Metadata-Version: 2.1
Name: nonebot-adapter-kritor
Version: 0.3.2
Summary: Nonebot Adapter for Kritor Protocol
Author-Email: rf_tar_railt <rf_tar_railt@qq.com>
License: MIT
Requires-Python: >=3.9
Requires-Dist: nonebot2>=2.2.1
Requires-Dist: betterproto>=2.0.0b7
